pytv/ModuleLoader.py
pytv/__init__.py
pytv/pytv.py
pytv/utils.py
PyTV_new-0.1.dist-info/LICENSE
PyTV_new-0.1.dist-info/METADATA
PyTV_new-0.1.dist-info/WHEEL
PyTV_new-0.1.dist-info/top_level.txt
PyTV_new-0.1.dist-info/RECORD
